{
  "main": {
    "id": "2f2f37685017e8f9",
    "type": "split",
    "children": [
      {
        "id": "dae8d071b0fd95e7",
        "type": "tabs",
        "children": [
          {
            "id": "fba309182b9c8b90",
            "type": "leaf",
            "state": {
              "type": "markdown",
              "state": {
                "file": "! Notes to make.md",
                "mode": "source",
                "source": false
              }
            }
          }
        ]
      }
    ],
    "direction": "vertical"
  },
  "left": {
    "id": "29a3db12c2955604",
    "type": "split",
    "children": [
      {
        "id": "1299c73736571a3c",
        "type": "tabs",
        "children": [
          {
            "id": "8765d05b662c1a75",
            "type": "leaf",
            "state": {
              "type": "file-explorer",
              "state": {
                "sortOrder": "alphabetical"
              }
            }
          },
          {
            "id": "3e8443b947304496",
            "type": "leaf",
            "state": {
              "type": "search",
              "state": {
                "query": "",
                "matchingCase": false,
                "explainSearch": false,
                "collapseAll": false,
                "extraContext": false,
                "sortOrder": "alphabetical"
              }
            }
          },
          {
            "id": "a2333c31529f89d9",
            "type": "leaf",
            "state": {
              "type": "bookmarks",
              "state": {}
            }
          }
        ]
      }
    ],
    "direction": "horizontal",
    "width": 300
  },
  "right": {
    "id": "eb71f236ac895639",
    "type": "split",
    "children": [
      {
        "id": "137fb8025a0923a4",
        "type": "tabs",
        "children": [
          {
            "id": "630c5537efe002c4",
            "type": "leaf",
            "state": {
              "type": "backlink",
              "state": {
                "file": "! Notes to make.md",
                "collapseAll": false,
                "extraContext": false,
                "sortOrder": "alphabetical",
                "showSearch": false,
                "searchQuery": "",
                "backlinkCollapsed": false,
                "unlinkedCollapsed": true
              }
            }
          },
          {
            "id": "77e068d87bf2ea31",
            "type": "leaf",
            "state": {
              "type": "outgoing-link",
              "state": {
                "file": "! Notes to make.md",
                "linksCollapsed": false,
                "unlinkedCollapsed": true
              }
            }
          },
          {
            "id": "ed2946af3e9508a5",
            "type": "leaf",
            "state": {
              "type": "tag",
              "state": {
                "sortOrder": "frequency",
                "useHierarchy": true
              }
            }
          },
          {
            "id": "431f7f97fa7015e2",
            "type": "leaf",
            "state": {
              "type": "outline",
              "state": {
                "file": "! Notes to make.md"
              }
            }
          },
          {
            "id": "e4557b425a12be0f",
            "type": "leaf",
            "state": {
              "type": "all-properties",
              "state": {
                "sortOrder": "frequency",
                "showSearch": false,
                "searchQuery": ""
              }
            }
          }
        ]
      }
    ],
    "direction": "horizontal",
    "width": 300,
    "collapsed": true
  },
  "left-ribbon": {
    "hiddenItems": {
      "switcher:Open quick switcher": false,
      "graph:Open graph view": false,
      "canvas:Create new canvas": false,
      "daily-notes:Open today's daily note": false,
      "templates:Insert template": false,
      "command-palette:Open command palette": false,
      "audio-recorder:Start/stop recording": false
    }
  },
  "active": "fba309182b9c8b90",
  "lastOpenFiles": [
    "README.md",
    "dotNET/API Backend/CORS.md",
    "! Notes to make.md",
    "dotNET/Dapper.md",
    "MS SQL Server/Value from another table.md",
    "TMP Get image.md",
    "MS SQL Server/Filestream/Data operations.md",
    "MS SQL Server/Filestream/Enable and configure.md",
    "MS SQL Server/Filestream/Create a table.md",
    "MS SQL Server/Constraints.md",
    "MS SQL Server/Filestream/Create a database.md",
    "MS SQL Server/Basic commands.md",
    "MS SQL Server/Data types.md",
    "dotNET/dotNET Framework Basics/try-catch.md",
    "[GitHub.md",
    "Structure.md",
    "Create.md",
    "MS SQL Server/Filtering.md",
    "dotNET/API Backend/Service responce.md",
    "dotNET/API Backend/Service.md",
    "dotNET/API Backend/Controller.md",
    "dotNET/API Backend/Create new API.md",
    "MS SQL Server/About MS SQL Server.md",
    "MS SQL Server/Functions.md",
    "dotNET/AutoMapper.md",
    "dotNET/API Backend/About ASP.NET API Backend.md",
    "MS SQL Server/Filestream",
    "dotNET/Dapper",
    "dotNET/dotNET Framework Basics",
    "MS SQL Server",
    "ASP.NET/Untitled",
    "Angular/API",
    "dotNET/API Backend",
    "dotNET",
    "Git",
    "Untitled.canvas",
    "Angular/Routing"
  ]
}